MONarchy/Analyse.py
MONarchy/MONarchy.py
MONarchy/__init__.py
MONarchy-1.0.15.dist-info/LICENSE
MONarchy-1.0.15.dist-info/METADATA
MONarchy-1.0.15.dist-info/WHEEL
MONarchy-1.0.15.dist-info/top_level.txt
MONarchy-1.0.15.dist-info/RECORD
