Metadata-Version: 2.1
Name: MONarchy
Version: 1.0.15
Summary: MON (Meadian of meaNs)
Home-page: https://github.com/prise-3d/MONarchy
Maintainer: Samuel DELEPOULLE
Maintainer-email: samuel.delepoulle@univ-littoral.fr
License: MIT
Platform: UNKNOWN
Classifier: Development Status :: 4 - Beta
Classifier: License :: OSI Approved :: MIT License
Classifier: Programming Language :: Python :: 3.7
Classifier: Topic :: Scientific/Engineering
Classifier: Topic :: Utilities
Requires-Dist: numpy
Requires-Dist: pandas
Requires-Dist: seaborn
